codde_protocol-0.1.6.dist-info/METADATA
codde_protocol-0.1.6.dist-info/WHEEL
codde_protocol-0.1.6.dist-info/license_files/LICENSE
codde_protocol/__init__.py
codde_protocol/codde_protocol.cpython-310-darwin.so
codde_protocol-0.1.6.dist-info/RECORD
