Metadata-Version: 2.3
Name: codde_protocol
Version: 0.1.6
Classifier: Programming Language :: Rust
Classifier: Programming Language :: Python :: Implementation :: CPython
Classifier: Programming Language :: Python :: Implementation :: PyPy
License-File: LICENSE
License-File: LICENSE
Summary: Multi Communication protocol in heart of the C.O.D.D.E. Pi framework
Keywords: rust,python,codde_pi,iot
Home-Page: https://github.com/codde-pi/codde_protocol
Author: Mathis Lecomte <vm.lecomte@gmail.com>
Author-email: Mathis Lecomte <vm.lecomte@gmail.com>
Requires-Python: >=3.8
Project-URL: Homepage, https://github.com/codde-pi/codde_protocol
Project-URL: Issues, https://github.com/codde-pi/codde_protocol/issues
Project-URL: Repository, https://github.com/codde-pi/codde_protocol.git
Project-URL: Changelog, https://github.com/codde-pi/codde_protocol/blob/main/CHANGELOG.md
